{
    "data": [
        {
            "title": "漫威复仇者联盟互动体验站点亮北京盛大启幕",
            "desc": "火爆全球的漫威复仇者联盟互动体验站(Marvel Avengers S.T.A.T.I.O.N.)，于2017年5月24日晚在北京朝阳公园08广场盛大启幕。香港著名导演唐季礼、著名导演胡",
            "date": "2017-05-25",
            "src": "http://www.sun-park.com/uploadfile/2017/0525/20170525093700437.jpg",
            "id": "879"
        },
        {
            "title": "“2017北京书市”助推首都全民阅读",
            "desc": "2017北京书市将于4月14日至24日 在朝阳公园精彩呈现。　　本届书市由北京市新闻出版广电局主办，北京发行集团、北京出版发行行业协会承办。书市秉持弘扬...",
            "date": "2017-05-25",
            "src": "http://www.sun-park.com/uploadfile/2017/0525/20170525093939326.jpg",
            "id": "879"
        },
        {
            "title": "“2017北京朝阳国际风情节”春节亮相朝阳公园",
            "desc": "看表演、品美食 市民可与艺术家“亲密互动” “2017北京朝阳国际风情节”春节亮相朝阳公园冬奥知识主题展同期开放 市民可免费了解冬奥常识 做“最有文化...",
            "date": "2017-05-25",
            "src": "http://www.sun-park.com/uploadfile/2017/0525/20170525094042595.jpg",
            "id": "879"
        },
        {
            "title": "漫威复仇者联盟互动体验站点亮北京盛大启幕",
            "desc": "火爆全球的漫威复仇者联盟互动体验站(Marvel Avengers S.T.A.T.I.O.N.)，于2017年5月24日晚在北京朝阳公园08广场盛大启幕。香港著名导演唐季礼、著名导演胡",
            "date": "2017-05-25",
            "src": "http://www.sun-park.com/uploadfile/2017/0525/20170525093700437.jpg",
            "id": "879"
        },
        {
            "title": "“2017北京书市”助推首都全民阅读",
            "desc": "2017北京书市将于4月14日至24日 在朝阳公园精彩呈现。　　本届书市由北京市新闻出版广电局主办，北京发行集团、北京出版发行行业协会承办。书市秉持弘扬...",
            "date": "2017-05-25",
            "src": "http://www.sun-park.com/uploadfile/2017/0525/20170525093939326.jpg",
            "id": "879"
        },
        {
            "title": "“2017北京朝阳国际风情节”春节亮相朝阳公园",
            "desc": "看表演、品美食 市民可与艺术家“亲密互动” “2017北京朝阳国际风情节”春节亮相朝阳公园冬奥知识主题展同期开放 市民可免费了解冬奥常识 做“最有文化...",
            "date": "2017-05-25",
            "src": "http://www.sun-park.com/uploadfile/2017/0525/20170525094042595.jpg",
            "id": "879"
        },
        {
            "title": "漫威复仇者联盟互动体验站点亮北京盛大启幕",
            "desc": "火爆全球的漫威复仇者联盟互动体验站(Marvel Avengers S.T.A.T.I.O.N.)，于2017年5月24日晚在北京朝阳公园08广场盛大启幕。香港著名导演唐季礼、著名导演胡",
            "date": "2017-05-25",
            "src": "http://www.sun-park.com/uploadfile/2017/0525/20170525093700437.jpg",
            "id": "879"
        },
        {
            "title": "“2017北京书市”助推首都全民阅读",
            "desc": "2017北京书市将于4月14日至24日 在朝阳公园精彩呈现。　　本届书市由北京市新闻出版广电局主办，北京发行集团、北京出版发行行业协会承办。书市秉持弘扬...",
            "date": "2017-05-25",
            "src": "http://www.sun-park.com/uploadfile/2017/0525/20170525093939326.jpg",
            "id": "879"
        },
        {
            "title": "“2017北京朝阳国际风情节”春节亮相朝阳公园",
            "desc": "看表演、品美食 市民可与艺术家“亲密互动” “2017北京朝阳国际风情节”春节亮相朝阳公园冬奥知识主题展同期开放 市民可免费了解冬奥常识 做“最有文化...",
            "date": "2017-05-25",
            "src": "http://www.sun-park.com/uploadfile/2017/0525/20170525094042595.jpg",
            "id": "879"
        },
        {
            "title": "漫威复仇者联盟互动体验站点亮北京盛大启幕",
            "desc": "火爆全球的漫威复仇者联盟互动体验站(Marvel Avengers S.T.A.T.I.O.N.)，于2017年5月24日晚在北京朝阳公园08广场盛大启幕。香港著名导演唐季礼、著名导演胡",
            "date": "2017-05-25",
            "src": "http://www.sun-park.com/uploadfile/2017/0525/20170525093700437.jpg",
            "id": "879"
        },
        {
            "title": "“2017北京书市”助推首都全民阅读",
            "desc": "2017北京书市将于4月14日至24日 在朝阳公园精彩呈现。　　本届书市由北京市新闻出版广电局主办，北京发行集团、北京出版发行行业协会承办。书市秉持弘扬...",
            "date": "2017-05-25",
            "src": "http://www.sun-park.com/uploadfile/2017/0525/20170525093939326.jpg",
            "id": "879"
        },
        {
            "title": "“2017北京朝阳国际风情节”春节亮相朝阳公园",
            "desc": "看表演、品美食 市民可与艺术家“亲密互动” “2017北京朝阳国际风情节”春节亮相朝阳公园冬奥知识主题展同期开放 市民可免费了解冬奥常识 做“最有文化...",
            "date": "2017-05-25",
            "src": "http://www.sun-park.com/uploadfile/2017/0525/20170525094042595.jpg",
            "id": "879"
        },
        {
            "title": "漫威复仇者联盟互动体验站点亮北京盛大启幕",
            "desc": "火爆全球的漫威复仇者联盟互动体验站(Marvel Avengers S.T.A.T.I.O.N.)，于2017年5月24日晚在北京朝阳公园08广场盛大启幕。香港著名导演唐季礼、著名导演胡",
            "date": "2017-05-25",
            "src": "http://www.sun-park.com/uploadfile/2017/0525/20170525093700437.jpg",
            "id": "879"
        },
        {
            "title": "“2017北京书市”助推首都全民阅读",
            "desc": "2017北京书市将于4月14日至24日 在朝阳公园精彩呈现。　　本届书市由北京市新闻出版广电局主办，北京发行集团、北京出版发行行业协会承办。书市秉持弘扬...",
            "date": "2017-05-25",
            "src": "http://www.sun-park.com/uploadfile/2017/0525/20170525093939326.jpg",
            "id": "879"
        },
        {
            "title": "“2017北京朝阳国际风情节”春节亮相朝阳公园",
            "desc": "看表演、品美食 市民可与艺术家“亲密互动” “2017北京朝阳国际风情节”春节亮相朝阳公园冬奥知识主题展同期开放 市民可免费了解冬奥常识 做“最有文化...",
            "date": "2017-05-25",
            "src": "http://www.sun-park.com/uploadfile/2017/0525/20170525094042595.jpg",
            "id": "879"
        }
    ]
}